{
	"tempHash": "00DB26B051E13092",
	"tbluHash": "004329A7DDD6B9FD",
	"rootEntity": "cafe1acd38c389e1",
	"entities": {
		"cafe52ef1e94105b": {
			"parent": "cafe1acd38c389e1",
			"name": "HeroA",
			"factory": "[modules:/zcharsetcharactertype.class].pc_entitytype",
			"blueprint": "[modules:/zcharsetcharactertype.class].pc_entityblueprint",
			"properties": {
				"m_aVariations": {
					"type": "TArray<SEntityTemplateReference>",
					"value": ["cafef591646cd459"],
					"postInit": true
				}
			}
		},
		"cafe13dfbaa36acd": {
			"parent": "cafe1acd38c389e1",
			"name": "Actor",
			"factory": "[modules:/zcharsetcharactertype.class].pc_entitytype",
			"blueprint": "[modules:/zcharsetcharactertype.class].pc_entityblueprint",
			"properties": {
				"m_aVariations": {
					"type": "TArray<SEntityTemplateReference>",
					"value": ["cafe28f7c68d4baf"],
					"postInit": true
				}
			}
		},
		"cafe28f7c68d4baf": {
			"parent": "cafe13dfbaa36acd",
			"name": "0",
			"factory": "[modules:/zoutfitvariation.class].pc_entitytype",
			"blueprint": "[modules:/zoutfitvariation.class].pc_entityblueprint",
			"properties": {
				"m_Outfit": {
					"type": "ZRuntimeResourceID",
					"value": {
						"resource": "[assembly:/_pro/characters/templates/colorado/char_hay.template?/outfit_entertainer_m_actor_v0.entitytemplate].pc_entitytemplate",
						"flag": "9F"
					}
				}
			}
		},
		"cafe06e8e5b5a804": {
			"parent": "cafea2ef74191e32",
			"name": "Var0",
			"factory": "[modules:/zoutfitvariation.class].pc_entitytype",
			"blueprint": "[modules:/zoutfitvariation.class].pc_entityblueprint",
			"properties": {
				"m_Outfit": {
					"type": "ZRuntimeResourceID",
					"value": {
						"resource": "[assembly:/_pro/characters/templates/magpie/char_magpie_guards.template?/outfit_magpie_guard_guardian_m_nude_v2.entitytemplate].pc_entitytemplate",
						"flag": "9F"
					}
				}
			}
		},
		"cafe1acd38c389e1": {
			"parent": null,
			"name": "CHARSET_entertainer_M",
			"factory": "[modules:/zoutfitvariationcollection.class].pc_entitytype",
			"blueprint": "[modules:/zoutfitvariationcollection.class].pc_entityblueprint",
			"properties": {
				"m_aCharacters": {
					"type": "TArray<SEntityTemplateReference>",
					"value": [
						"cafe13dfbaa36acd",
						"cafea2ef74191e32",
						"cafe52ef1e94105b"
					],
					"postInit": true
				}
			}
		},
		"cafef591646cd459": {
			"parent": "cafe52ef1e94105b",
			"name": "Var0",
			"factory": "[modules:/zoutfitvariation.class].pc_entitytype",
			"blueprint": "[modules:/zoutfitvariation.class].pc_entityblueprint",
			"properties": {
				"m_Outfit": {
					"type": "ZRuntimeResourceID",
					"value": {
						"resource": "[assembly:/_pro/characters/templates/colorado/char_hay.template?/outfit_entertainer_m_hero_v0.entitytemplate].pc_entitytemplate",
						"flag": "9F"
					}
				}
			}
		},
		"cafea2ef74191e32": {
			"parent": "cafe1acd38c389e1",
			"name": "Nude",
			"factory": "[modules:/zcharsetcharactertype.class].pc_entitytype",
			"blueprint": "[modules:/zcharsetcharactertype.class].pc_entityblueprint",
			"properties": {
				"m_aVariations": {
					"type": "TArray<SEntityTemplateReference>",
					"value": ["cafe06e8e5b5a804"]
				}
			}
		}
	},
	"propertyOverrides": [],
	"overrideDeletes": [],
	"pinConnectionOverrides": [],
	"pinConnectionOverrideDeletes": [],
	"externalScenes": [],
	"subType": "template",
	"quickEntityVersion": 3.1,
	"extraFactoryDependencies": [],
	"extraBlueprintDependencies": [],
	"comments": []
}
