{
	"tempHash": "006C29190AB0FAD6",
	"tbluHash": "005D1893ABB58B5C",
	"rootEntity": "cafec5121d9aa358",
	"entities": {
		"cafeb1130dc42d48": {
			"parent": "cafec5121d9aa358",
			"name": "Shirt_Dress_Torso_BtnUp_Tkd_3open",
			"factory": "[assembly:/_pro/characters/templates/_part_library/male_apparel/male_reg_apparel_torso_l01.template?/shirt_dress_torso_btnup_tkd_3open.entitytemplate].pc_entitytype",
			"blueprint": "[assembly:/_pro/characters/templates/_part_library/male_apparel/male_reg_apparel_torso_l01.template?/shirt_dress_torso_btnup_tkd_3open.entitytemplate].pc_entityblueprint",
			"properties": {
				"Diffuse_Color_01_Value": {
					"type": "SColorRGB",
					"value": "#8acae6"
				},
				"Texture2D_01": {
					"type": "ZRuntimeResourceID",
					"value": {
						"resource": "[assembly:/_pro/characters/assets/_apparel/male/volumes_l01/dress_shirt/textures/male_reg_dress_shirt.texture?/diffuse_a_ao.tex](ascolormap).pc_tex",
						"flag": "5F"
					}
				},
				"Diffuse_Color_01_Value_1": {
					"type": "SColorRGB",
					"value": "#425757"
				}
			}
		},
		"cafed54c8f6c34bd": {
			"parent": "cafec5121d9aa358",
			"name": "Mesh_Bandana_Tied",
			"factory": "[modules:/zbodypartentity.class].pc_entitytype",
			"blueprint": "[modules:/zbodypartentity.class].pc_entityblueprint",
			"properties": {
				"m_pMeshResource": {
					"type": "ZRuntimeResourceID",
					"value": {
						"resource": "[assembly:/_pro/characters/assets/guards/llama/yatesestatelowtier/geometry/male_reg_yatesestatelowtier.wl2?/bandana_tied.weightedprim](bodypart).pc_weightedprim",
						"flag": "5F"
					}
				}
			}
		},
		"cafec3ec5f9b5c39": {
			"parent": "cafed54c8f6c34bd",
			"name": "darkandstormy_scarf",
			"factory": "[assembly:/_pro/characters/assets/individuals/italy/elusive_target_darkandstormy/materials/darkandstormy_scarf.mi].pc_entitytype",
			"blueprint": "[assembly:/_pro/characters/assets/individuals/italy/elusive_target_darkandstormy/materials/darkandstormy_scarf.mi].pc_entityblueprint",
			"properties": {
				"m_mTransform": {
					"type": "SMatrix43",
					"value": {
						"rotation": {
							"x": -0.0,
							"y": 0.0,
							"z": 26.614735026983496
						},
						"position": {
							"x": 0.27743101119995117,
							"y": 0.06810499727725983,
							"z": -0.03514600172638893
						}
					}
				},
				"Clients": {
					"type": "TArray<SEntityTemplateReference>",
					"value": ["cafed54c8f6c34bd"]
				},
				"Texture2D_01_enab": { "type": "bool", "value": true },
				"Texture2D_01": {
					"type": "ZRuntimeResourceID",
					"value": {
						"resource": "[assembly:/_pro/characters/assets/individuals/italy/elusive_target_darkandstormy/textures/darkandstormy_scarf.texture?/diffuse_dirty.tex](ascolormap).pc_tex",
						"flag": "5F"
					}
				},
				"ConstantColorRGB_02_Value": {
					"type": "SColorRGB",
					"value": "#4f4f4f"
				},
				"ConstantColorRGB_02_Value_op": {
					"type": "IRenderMaterialEntity.EModifierOperation",
					"value": "eReplace"
				},
				"Texture2D_03_enab": { "type": "bool", "value": true },
				"ConstantVector1D_09_Value_op": {
					"type": "IRenderMaterialEntity.EModifierOperation",
					"value": "eReplace"
				},
				"ConstantVector1D_03_Value_op": {
					"type": "IRenderMaterialEntity.EModifierOperation",
					"value": "eReplace"
				},
				"ConstantVector1D_03_Value": {
					"type": "float32",
					"value": 0.0
				},
				"ConstantVector1D_05_Value_op": {
					"type": "IRenderMaterialEntity.EModifierOperation",
					"value": "eReplace"
				},
				"ConstantVector1D_05_Value": {
					"type": "float32",
					"value": 0.4600000083446502
				},
				"m_eidParent": {
					"type": "SEntityTemplateReference",
					"value": "cafec5121d9aa358",
					"postInit": true
				}
			}
		},
		"cafee8dd417bdf63": {
			"parent": "cafec5121d9aa358",
			"name": "Arms_Elbow_Hand",
			"factory": "[assembly:/_pro/characters/templates/_part_library/male_parts/male_reg_bodyparts.template?/arms_elbow_hand.entitytemplate].pc_entitytype",
			"blueprint": "[assembly:/_pro/characters/templates/_part_library/male_parts/male_reg_bodyparts.template?/arms_elbow_hand.entitytemplate].pc_entityblueprint"
		},
		"cafeeb591b15666c": {
			"parent": "cafec5121d9aa358",
			"name": "Hair_Full_Bald_MS",
			"factory": "[assembly:/_pro/characters/templates/_part_library/male_parts/male_hair.template?/hair_full_bald_ms.entitytemplate].pc_entitytype",
			"blueprint": "[assembly:/_pro/characters/templates/_part_library/male_parts/male_hair.template?/hair_full_bald_ms.entitytemplate].pc_entityblueprint",
			"properties": {
				"ConstantColorRGB_02_Value": {
					"type": "SColorRGB",
					"value": "#26201a"
				},
				"ConstantColorRGB_05_Value": {
					"type": "SColorRGB",
					"value": "#ffe1d4"
				},
				"ConstantColorRGB_03_Value": {
					"type": "SColorRGB",
					"value": "#302a24"
				},
				"ConstantVector1D_05_Value": {
					"type": "float32",
					"value": 0.3400000035762787
				}
			}
		},
		"cafe8a44bd53c25f": {
			"parent": "cafec5121d9aa358",
			"name": "Beard_Cap",
			"factory": "[assembly:/_pro/characters/templates/_part_library/male_parts/male_facialhair.template?/beard_cap.entitytemplate].pc_entitytype",
			"blueprint": "[assembly:/_pro/characters/templates/_part_library/male_parts/male_facialhair.template?/beard_cap.entitytemplate].pc_entityblueprint"
		},
		"cafec5121d9aa358": {
			"parent": null,
			"name": "OUTFIT_Hay_guard_VIP_V0",
			"factory": "[assembly:/_pro/characters/templates/_sourcefiles/outfit.template?/outfit_base.entitytemplate].pc_entitytype",
			"blueprint": "[assembly:/_pro/characters/templates/_sourcefiles/outfit.template?/outfit_base.entitytemplate].pc_entityblueprint",
			"properties": {
				"m_pBonesAndCollisionResource": {
					"type": "ZRuntimeResourceID",
					"value": {
						"resource": "[assembly:/_pro/characters/assets/_sourcefiles/male_reg/geometry/male_reg.wl2?/bones.weightedprim](bodypart).pc_bonerig",
						"flag": "5F"
					}
				},
				"m_LocalColliders": {
					"type": "TArray<SEntityTemplateReference>",
					"value": []
				},
				"m_eRoomBehaviour": {
					"type": "ZSpatialEntity.ERoomBehaviour",
					"value": "ROOM_DYNAMIC"
				},
				"m_fFrustumFarDistanceProperty": {
					"type": "float32",
					"value": 10.0
				},
				"m_mTransform": {
					"type": "SMatrix43",
					"value": {
						"rotation": {
							"x": -0.0,
							"y": 0.0,
							"z": -11.062815397163837
						},
						"position": { "x": 0.0, "y": 0.0, "z": 0.0 }
					}
				},
				"m_aBodyParts": {
					"type": "TArray<SEntityTemplateReference>",
					"value": [
						"cafeb1130dc42d48",
						"cafe796ae6e644dd",
						"cafed54c8f6c34bd",
						"cafe8a44bd53c25f",
						"cafe4a1ed980e4ce",
						"cafee8dd417bdf63",
						"cafeeb591b15666c",
						"cafe41c043c1acf0",
						"cafe13f5d62971b3",
						"cafef4ced13d42b0"
					],
					"postInit": true
				}
			}
		},
		"cafe4a1ed980e4ce": {
			"parent": "cafec5121d9aa358",
			"name": "Shirt_Dress_Sleeves_Rolled",
			"factory": "[assembly:/_pro/characters/templates/_part_library/male_apparel/male_reg_apparel_torso_l01.template?/shirt_dress_sleeves_rolled.entitytemplate].pc_entitytype",
			"blueprint": "[assembly:/_pro/characters/templates/_part_library/male_apparel/male_reg_apparel_torso_l01.template?/shirt_dress_sleeves_rolled.entitytemplate].pc_entityblueprint",
			"properties": {
				"Diffuse_Color_01_Value": {
					"type": "SColorRGB",
					"value": "#8acae6"
				},
				"ConstantVector1D_01_Value": {
					"type": "float32",
					"value": 0.5
				},
				"Texture2D_01": {
					"type": "ZRuntimeResourceID",
					"value": {
						"resource": "[assembly:/_pro/characters/assets/_apparel/male/volumes_l01/dress_shirt/textures/male_reg_dress_shirt_short_sleeves.texture?/diffuse_sweaty.tex](ascolormap).pc_tex",
						"flag": "5F"
					}
				}
			}
		},
		"cafe796ae6e644dd": {
			"parent": "cafec5121d9aa358",
			"name": "Torso_Neck_LowCut",
			"factory": "[assembly:/_pro/characters/templates/_part_library/male_parts/male_reg_bodyparts.template?/torso_neck_lowcut.entitytemplate].pc_entitytype",
			"blueprint": "[assembly:/_pro/characters/templates/_part_library/male_parts/male_reg_bodyparts.template?/torso_neck_lowcut.entitytemplate].pc_entityblueprint"
		},
		"cafe41c043c1acf0": {
			"parent": "cafec5121d9aa358",
			"name": "Head_Base",
			"factory": "[assembly:/_pro/characters/templates/_part_library/male_parts/male_heads_caucasian.template?/head_base.entitytemplate].pc_entitytype",
			"blueprint": "[assembly:/_pro/characters/templates/_part_library/male_parts/male_heads_caucasian.template?/head_base.entitytemplate].pc_entityblueprint"
		},
		"cafe13f5d62971b3": {
			"parent": "cafec5121d9aa358",
			"name": "Pants_Jeans_Baggy",
			"factory": "[assembly:/_pro/characters/templates/_part_library/male_apparel/male_reg_apparel_legs.template?/pants_jeans_baggy.entitytemplate].pc_entitytype",
			"blueprint": "[assembly:/_pro/characters/templates/_part_library/male_apparel/male_reg_apparel_legs.template?/pants_jeans_baggy.entitytemplate].pc_entityblueprint",
			"properties": {
				"Diffuse_Color_01_Value": {
					"type": "SColorRGB",
					"value": "#57524c"
				}
			}
		},
		"cafef4ced13d42b0": {
			"parent": "cafec5121d9aa358",
			"name": "Shoes_Boots",
			"factory": "[assembly:/_pro/characters/templates/_part_library/male_apparel/male_reg_apparel_feet.template?/shoes_boots_ankle.entitytemplate].pc_entitytype",
			"blueprint": "[assembly:/_pro/characters/templates/_part_library/male_apparel/male_reg_apparel_feet.template?/shoes_boots_ankle.entitytemplate].pc_entityblueprint",
			"properties": {
				"Diffuse_Color_01_Value": {
					"type": "SColorRGB",
					"value": "#383838"
				},
				"ConstantVector1D_04_Value": {
					"type": "float32",
					"value": 0.12999999523162842
				},
				"ConstantVector1D_05_Value": {
					"type": "float32",
					"value": 1.4700000286102295
				},
				"m_pMeshResource": {
					"type": "ZRuntimeResourceID",
					"value": {
						"resource": "[assembly:/_pro/characters/assets/_apparel/male/volumes_l01/shoes/geometry/male_reg_shoes.wl2?/shoes_boots_cowboy_cut.weightedprim](bodypart).pc_weightedprim",
						"flag": "5F"
					}
				}
			}
		},
		"cafed62c7560d688": {
			"parent": "cafec5121d9aa358",
			"name": "Attacher_Head",
			"factory": "[assembly:/templates/aspectdummy.aspect]([modules:/zcompositeentity.class].entitytype,[modules:/zboneattachaspect.class].entitytype).pc_entitytype",
			"blueprint": "[assembly:/templates/aspectdummy.aspect]([modules:/zcompositeentity.class].entitytype,[modules:/zboneattachaspect.class].entitytype).pc_entityblueprint",
			"properties": {
				"m_BoneName": { "type": "ZString", "value": "Head" },
				"m_linkedEntity": {
					"type": "SEntityTemplateReference",
					"value": "cafec5121d9aa358",
					"postInit": true
				},
				"m_eidParent": {
					"type": "SEntityTemplateReference",
					"value": "cafec5121d9aa358",
					"postInit": true
				}
			}
		},
		"cafe56ca92eda496": {
			"parent": "cafed62c7560d688",
			"name": "hat_cowboy",
			"factory": "[assembly:/_pro/characters/templates/_part_library/male_apparel/male_apparel_headwear_prim.template?/hat_cowboy.entitytemplate].pc_entitytype",
			"blueprint": "[assembly:/_pro/characters/templates/_part_library/male_apparel/male_apparel_headwear_prim.template?/hat_cowboy.entitytemplate].pc_entityblueprint",
			"properties": {
				"m_mTransform": {
					"type": "SMatrix43",
					"value": {
						"rotation": {
							"x": 76.7787077263265,
							"y": 86.88942111084724,
							"z": 102.25221161199164
						},
						"position": {
							"x": 0.09582500159740448,
							"y": 0.018059000372886658,
							"z": 0.0023089998867362738
						}
					}
				},
				"Diffuse_Color_01_Value": {
					"type": "SColorRGB",
					"value": "#dfdfdf"
				},
				"m_PrimitiveScale": {
					"type": "SVector3",
					"value": {
						"x": 1.0239399671554563,
						"y": 1.0,
						"z": 1.0
					}
				},
				"m_eidParent": {
					"type": "SEntityTemplateReference",
					"value": "cafed62c7560d688"
				}
			}
		}
	},
	"propertyOverrides": [],
	"overrideDeletes": [],
	"pinConnectionOverrides": [],
	"pinConnectionOverrideDeletes": [],
	"externalScenes": [],
	"subType": "template",
	"quickEntityVersion": 3.1,
	"extraFactoryDependencies": [],
	"extraBlueprintDependencies": [],
	"comments": []
}
